nugu/__init__.py
nugu/module.py
nugu-0.3.dist-info/METADATA
nugu-0.3.dist-info/WHEEL
nugu-0.3.dist-info/top_level.txt
nugu-0.3.dist-info/RECORD
