Metadata-Version: 2.1
Name: nugu
Version: 0.3
Summary: About nugu prgrammer named YangChoi
Home-page: https://github.com/yangchoi/nugu
Author: YangChoi
Author-email: yangchoi.hj@gmail.com
Classifier: Programming Language :: Python :: 3
Classifier: License :: OSI Approved :: MIT License
Classifier: Operating System :: OS Independent
Requires-Python: >=3.6
